LICENSE
MANIFEST.in
README.md
pytest_ok.py
setup.py
pytest_ok.egg-info/PKG-INFO
pytest_ok.egg-info/SOURCES.txt
pytest_ok.egg-info/dependency_links.txt
pytest_ok.egg-info/entry_points.txt
pytest_ok.egg-info/requires.txt
pytest_ok.egg-info/top_level.txt